kineticmodels/__init__.py
kineticmodels/inhibition_models.py
kineticmodels/uptake_models.py
tests/__init__.py
tests/test_inhibition_models.py
tests/test_uptake_models.py
kineticmodels-0.0.15.dist-info/LICENSE
kineticmodels-0.0.15.dist-info/METADATA
kineticmodels-0.0.15.dist-info/WHEEL
kineticmodels-0.0.15.dist-info/top_level.txt
kineticmodels-0.0.15.dist-info/RECORD
