Metadata-Version: 2.1
Name: kineticmodels
Version: 0.0.15
Summary: tool including most used function.
Home-page: https://github.com/paucablop/fermentation.kinetic.models
Author: Pau Cabaneros
Author-email: pau.cabaneros@gmail.com
Project-URL: Bug Tracker, https://github.com/paucablop/fermentation.kinetic.models/issues/
Classifier: Programming Language :: Python :: 3
Classifier: License :: OSI Approved :: MIT License
Classifier: Operating System :: OS Independent
Requires-Python: >=3.10
License-File: LICENSE
Requires-Dist: numpy (>=1.23.2)
